{
  "language": "豪萨语",
  "tables": [
    {
      "type": "person",
      "headers": [
        "",
        "輔音",
        "b",
        "c",
        "d",
        "f",
        "g",
        "h",
        "jdj",
        "k",
        "l",
        "m",
        "n",
        "r",
        "s",
        "t",
        "w",
        "y",
        "z",
        "chsh",
        "gw",
        "ts",
        "kw"
      ],
      "rows": [
        {
          "key": "",
          "values": [
            "元音",
            "",
            "布",
            "奇",
            "德",
            "夫(弗)",
            "格",
            "赫",
            "杰",
            "克",
            "爾",
            "姆",
            "恩",
            "爾",
            "斯",
            "特",
            "夫(弗)",
            "伊",
            "茲",
            "什",
            "古",
            "茨",
            "库"
          ]
        },
        {
          "key": "",
          "values": [
            "a",
            "阿",
            "巴",
            "查",
            "達",
            "法",
            "加",
            "哈",
            "賈",
            "卡",
            "拉",
            "馬(瑪)",
            "納(娜)",
            "拉",
            "薩",
            "塔",
            "瓦",
            "亞(婭)",
            "扎",
            "沙(莎)",
            "瓜",
            "察",
            "夸"
          ]
        },
        {
          "key": "",
          "values": [
            "e",
            "埃",
            "貝",
            "切",
            "代(德)",
            "費",
            "蓋",
            "海",
            "杰",
            "凯",
            "萊",
            "梅",
            "內",
            "雷(蕾)",
            "塞",
            "泰",
            "韋",
            "耶",
            "澤",
            "谢",
            "圭",
            "采",
            "奎"
          ]
        },
        {
          "key": "",
          "values": [
            "i y",
            "伊",
            "比",
            "奇",
            "迪",
            "菲",
            "吉",
            "希",
            "吉",
            "基",
            "利(莉)",
            "米",
            "尼(妮)",
            "里(丽)",
            "西",
            "蒂",
            "維",
            "伊",
            "齊",
            "希",
            "圭",
            "齐",
            "奎"
          ]
        },
        {
          "key": "",
          "values": [
            "o",
            "奧",
            "博",
            "喬",
            "多",
            "福",
            "戈",
            "霍",
            "乔",
            "科",
            "洛",
            "莫",
            "諾",
            "羅(蘿)",
            "索",
            "托",
            "沃",
            "約",
            "佐",
            "绍",
            "果",
            "措",
            "阔"
          ]
        },
        {
          "key": "",
          "values": [
            "u",
            "烏",
            "布",
            "丘",
            "杜",
            "富",
            "古",
            "胡",
            "朱",
            "库",
            "卢",
            "穆",
            "努",
            "魯",
            "蘇",
            "圖",
            "武",
            "尤",
            "祖",
            "舒",
            "古",
            "楚",
            "库"
          ]
        },
        {
          "key": "",
          "values": [
            "an",
            "安",
            "班",
            "錢",
            "丹",
            "凡",
            "甘",
            "汉",
            "詹",
            "坎",
            "蘭",
            "曼",
            "南",
            "兰",
            "桑",
            "坦",
            "萬",
            "揚",
            "贊",
            "尚",
            "关",
            "灿",
            "宽"
          ]
        },
        {
          "key": "",
          "values": [
            "au aw",
            "奧",
            "鲍",
            "喬",
            "道",
            "福",
            "高",
            "豪",
            "乔",
            "考",
            "勞",
            "毛",
            "瑙",
            "勞",
            "紹",
            "陶",
            "沃",
            "堯",
            "藻",
            "绍",
            "",
            "曹",
            ""
          ]
        },
        {
          "key": "",
          "values": [
            "en",
            "恩",
            "本",
            "琴",
            "登",
            "芬",
            "根",
            "亨",
            "真",
            "肯",
            "倫",
            "門",
            "嫩",
            "倫",
            "森",
            "滕",
            "文",
            "延",
            "曾",
            "申",
            "古文",
            "岑",
            "昆"
          ]
        },
        {
          "key": "",
          "values": [
            "in",
            "因",
            "賓",
            "欽",
            "丁",
            "芬",
            "金",
            "欣",
            "金",
            "金",
            "林(琳)",
            "明",
            "寧",
            "林(琳)",
            "辛",
            "廷",
            "溫",
            "因",
            "津",
            "欣",
            "古温",
            "钦",
            "昆"
          ]
        },
        {
          "key": "",
          "values": [
            "on",
            "翁",
            "邦",
            "琼",
            "東",
            "豐",
            "貢",
            "洪",
            "琼",
            "孔",
            "隆",
            "蒙",
            "农",
            "龙",
            "松",
            "通",
            "翁",
            "永",
            "宗",
            "雄",
            "贡",
            "聪",
            "孔"
          ]
        },
        {
          "key": "",
          "values": [
            "un",
            "溫",
            "本",
            "春",
            "敦",
            "豐",
            "貢",
            "洪",
            "均",
            "昆",
            "倫",
            "蒙",
            "农",
            "倫",
            "孫",
            "通",
            "文",
            "雲",
            "尊",
            "顺",
            "贡",
            "聪",
            "昆"
          ]
        }
      ]
    }
  ],
  "raw_note": ""
}